LICENCE
README.md
setup.py
PyGlobalPrinter/__init__.py
PyGlobalPrinter.egg-info/PKG-INFO
PyGlobalPrinter.egg-info/SOURCES.txt
PyGlobalPrinter.egg-info/dependency_links.txt
PyGlobalPrinter.egg-info/top_level.txt