Metadata-Version: 2.4
Name: PyGlobalPrinter
Version: 0.0.1
Summary: A tool when you have one more threading in a program and need to print.
Home-page: https://github.com/wayne931121/
Author: wayne931121
Author-email: 
License: Attribution 4.0 International, Copyright (c) 2025 Wayne931121.
Classifier: Programming Language :: Python :: 3
Classifier: Operating System :: OS Independent
Requires-Python: >=3.0
License-File: LICENCE
Dynamic: author
Dynamic: classifier
Dynamic: description
Dynamic: description-content-type
Dynamic: home-page
Dynamic: license
Dynamic: license-file
Dynamic: requires-python
Dynamic: summary
